pycentral/__init__.py
pycentral/audit_logs.py
pycentral/base.py
pycentral/base_utils.py
pycentral/configuration.py
pycentral/constants.py
pycentral/device_inventory.py
pycentral/firmware_management.py
pycentral/licensing.py
pycentral/monitoring.py
pycentral/msp.py
pycentral/rapids.py
pycentral/refresh_api_token.py
pycentral/topology.py
pycentral/url_utils.py
pycentral/user_management.py
pycentral/visualrf.py
pycentral/workflows/__init__.py
pycentral/workflows/workflows_utils.py
pycentral-1.4.1.dist-info/LICENSE
pycentral-1.4.1.dist-info/METADATA
pycentral-1.4.1.dist-info/WHEEL
pycentral-1.4.1.dist-info/top_level.txt
pycentral-1.4.1.dist-info/RECORD
