Metadata-Version: 2.1
Name: pycentral
Version: 1.4.1
Summary: Aruba Central Python Package
Home-page: https://github.com/aruba/pycentral
Author: aruba-automation
Author-email: aruba-automation@hpe.com
Classifier: Programming Language :: Python :: 3 :: Only
Classifier: License :: OSI Approved :: MIT License
Classifier: Operating System :: OS Independent
Classifier: Intended Audience :: System Administrators
Classifier: Topic :: System :: Networking
Classifier: Development Status :: 4 - Beta
Requires-Python: >=3.8
License-File: LICENSE
Requires-Dist: requests ==2.31.0
Requires-Dist: PyYAML ==6.0.1
Requires-Dist: urllib3 ==2.2.2
Requires-Dist: certifi ==2024.7.4
Provides-Extra: colorlog
Requires-Dist: colorlog ; extra == 'colorlog'
